surf_controller/__init__.py
surf_controller/api.py
surf_controller/config.toml
surf_controller/gui.py
surf_controller/setup.py
surf_controller/utils.py
surf_controller-1.1.3.dist-info/METADATA
surf_controller-1.1.3.dist-info/WHEEL
surf_controller-1.1.3.dist-info/entry_points.txt
surf_controller-1.1.3.dist-info/licenses/LICENSE
surf_controller-1.1.3.dist-info/RECORD
