Metadata-Version: 2.4
Name: surf-controller
Version: 1.1.3
Summary: CLI interface to control SURF VMs
Author-email: Raoul Grouls <Raoul.Grouls@han.nl>
License-File: LICENSE
Requires-Python: >=3.11
Requires-Dist: requests>=2.32.3
